opentelemetry/propagators/jaeger/__init__.py
opentelemetry/propagators/jaeger/py.typed
opentelemetry/propagators/jaeger/version/__init__.py
opentelemetry_propagator_jaeger-1.39.0.dist-info/METADATA
opentelemetry_propagator_jaeger-1.39.0.dist-info/WHEEL
opentelemetry_propagator_jaeger-1.39.0.dist-info/entry_points.txt
opentelemetry_propagator_jaeger-1.39.0.dist-info/licenses/LICENSE
opentelemetry_propagator_jaeger-1.39.0.dist-info/RECORD
